processpype/__init__.py
processpype/core/__init__.py
processpype/core/application.py
processpype/core/configuration/__init__.py
processpype/core/configuration/manager.py
processpype/core/configuration/models.py
processpype/core/configuration/providers.py
processpype/core/logfire.py
processpype/core/manager.py
processpype/core/models.py
processpype/core/router.py
processpype/core/service/__init__.py
processpype/core/service/manager.py
processpype/core/service/router.py
processpype/core/service/service.py
processpype/core/system.py
processpype/creator.py
processpype/main.py
processpype/services/__init__.py
processpype/services/agent/__init__.py
processpype/services/agent/configuration.py
processpype/services/agent/manager.py
processpype/services/agent/router.py
processpype/services/agent/service.py
processpype/services/clock/__init__.py
processpype/services/clock/config.py
processpype/services/clock/manager.py
processpype/services/clock/router.py
processpype/services/clock/service.py
processpype/services/database/__init__.py
processpype/services/database/engines/__init__.py
processpype/services/database/engines/postgres.py
processpype/services/database/engines/sqlite.py
processpype/services/database/manager.py
processpype/services/database/models.py
processpype/services/database/service.py
processpype/services/monitoring/__init__.py
processpype/services/monitoring/cloudwatch/__init__.py
processpype/services/monitoring/cloudwatch/config.py
processpype/services/monitoring/cloudwatch/manager.py
processpype/services/monitoring/cloudwatch/router.py
processpype/services/monitoring/cloudwatch/service.py
processpype/services/monitoring/cronitor/__init__.py
processpype/services/monitoring/cronitor/config.py
processpype/services/monitoring/cronitor/manager.py
processpype/services/monitoring/cronitor/router.py
processpype/services/monitoring/cronitor/service.py
processpype/services/monitoring/system/__init__.py
processpype/services/monitoring/system/config.py
processpype-1.1.6.dist-info/LICENSE
processpype-1.1.6.dist-info/METADATA
processpype-1.1.6.dist-info/WHEEL
processpype-1.1.6.dist-info/RECORD
