Metadata-Version: 2.3
Name: processpype
Version: 1.1.6
Summary: A modular application framework with built-in FastAPI integration and pluggable services
Author: Gianluca Pagliara
Author-email: pagliara.gianluca@gmail.com
Requires-Python: >=3.13,<4.0
Classifier: Programming Language :: Python :: 3
Classifier: Programming Language :: Python :: 3.13
Provides-Extra: agents
Provides-Extra: all
Provides-Extra: all-py313
Provides-Extra: database
Provides-Extra: database-py313
Provides-Extra: monitoring
Provides-Extra: notifications
Provides-Extra: storage
Requires-Dist: agentspype (>=0.1.3,<0.2.0) ; extra == "agents" or extra == "all" or extra == "all-py313"
Requires-Dist: aiosmtplib (>=3.0.1,<4.0.0) ; extra == "notifications" or extra == "all" or extra == "all-py313"
Requires-Dist: aiosqlite (>=0.20.0,<0.21.0) ; extra == "database" or extra == "database-py313" or extra == "all" or extra == "all-py313"
Requires-Dist: asyncpg (>=0.29.0,<0.30.0) ; (python_version < "3.13") and (extra == "database" or extra == "all")
Requires-Dist: boto3 (>=1.37.0,<2.0.0) ; extra == "storage" or extra == "monitoring" or extra == "all" or extra == "all-py313"
Requires-Dist: chronopype (>=0.2.7,<0.3.0)
Requires-Dist: cronitor (==4.7.1) ; extra == "monitoring" or extra == "all" or extra == "all-py313"
Requires-Dist: eventspype (>=1.0.3,<2.0.0)
Requires-Dist: fastapi (>=0.115.6,<0.116.0)
Requires-Dist: httpx (>=0.28.1,<0.29.0)
Requires-Dist: logfire[fastapi] (>=4.16,<5.0)
Requires-Dist: psutil (>=6.1.1,<7.0.0)
Requires-Dist: pydantic (>=2.10.4,<3.0.0)
Requires-Dist: pytz (>=2024.2,<2025.0)
Requires-Dist: pyyaml (>=6.0.2,<7.0.0)
Requires-Dist: sqlalchemy (>=2.0.30,<3.0.0) ; extra == "database" or extra == "database-py313" or extra == "all" or extra == "all-py313"
Requires-Dist: telethon (>=1.34.0,<2.0.0) ; extra == "notifications" or extra == "all" or extra == "all-py313"
Requires-Dist: uvicorn (>=0.34.0,<0.35.0)
Project-URL: Repository, https://github.com/gianlucapagliara/processpype
